flowgate/__init__.py
flowgate/command_handler.py
flowgate/consumer.py
flowgate/event_handler.py
flowgate/handler.py
flowgate/message.py
flowgate/serializers.py
flowgate/utils.py
flowgate/messagebus/__init__.py
flowgate/messagebus/base.py
flowgate/messagebus/messagebus.py
flowgate/messagebus/kafka/__init__.py
flowgate/messagebus/kafka/avro.py
flowgate/messagebus/kafka/config.py
flowgate/messagebus/kafka/offset_watchdog/__init__.py
flowgate/messagebus/kafka/offset_watchdog/base.py
flowgate/messagebus/kafka/offset_watchdog/memory.py
flowgate/messagebus/kafka/offset_watchdog/null.py
flowgate/messagebus/kafka/offset_watchdog/redis.py
flowgate/messagebus/testing/__init__.py
flowgate/messagebus/testing/kafka.py
flowgate/messagebus/testing/utils.py
flowgate/services/__init__.py
flowgate/services/kafka/__init__.py
flowgate/services/kafka/avro/__init__.py
flowgate/services/kafka/avro/config.py
flowgate/services/kafka/avro/consumer.py
flowgate/services/kafka/avro/exceptions.py
flowgate/services/kafka/avro/message.py
flowgate/services/kafka/avro/producer.py
flowgate/services/kafka/avro/schema_registry.py
flowgate/services/kafka/avro/utils.py
flowgate-0.0.5.dist-info/METADATA
flowgate-0.0.5.dist-info/WHEEL
flowgate-0.0.5.dist-info/RECORD
