Metadata-Version: 2.4
Name: flowgate
Version: 0.0.5
Summary: Flowgate is a kafka client library for building event-driven systems.
Project-URL: Homepage, https://github.com/nf1s/flowgate
Project-URL: Issues, https://github.com/nf1s/flowgate/issues
Author-email: nf1s <ahmed.nafies@gmail.com>
License: MIT
Classifier: License :: OSI Approved :: MIT License
Classifier: Operating System :: OS Independent
Classifier: Programming Language :: Python :: 3
Requires-Dist: confluent-kafka>=1.8.2
Requires-Dist: confluent-kafka[avro]>=1.8.2
Requires-Dist: jsonpickle>=0.9.6
Requires-Dist: structlog>=17.2.0
Provides-Extra: cnamedtuple
Requires-Dist: cnamedtuple>=0.1.6; extra == 'cnamedtuple'
Provides-Extra: dev
Requires-Dist: fakeredis; extra == 'dev'
Requires-Dist: flake8; extra == 'dev'
Requires-Dist: flake8-eradicate; extra == 'dev'
Requires-Dist: flake8-isort; extra == 'dev'
Requires-Dist: ipdb; extra == 'dev'
Requires-Dist: isort; extra == 'dev'
Requires-Dist: mongomock; extra == 'dev'
Requires-Dist: mypy; extra == 'dev'
Requires-Dist: pdbpp; extra == 'dev'
Requires-Dist: pytest; extra == 'dev'
Requires-Dist: pytest-coverage; extra == 'dev'
Requires-Dist: pytest-mock; extra == 'dev'
Requires-Dist: pytest-sugar; extra == 'dev'
Requires-Dist: types-redis; extra == 'dev'
Requires-Dist: yapf; extra == 'dev'
Provides-Extra: mongo
Requires-Dist: pymongo>=3.6.1; extra == 'mongo'
Provides-Extra: redis
Requires-Dist: hiredis>=0.2.0; extra == 'redis'
Requires-Dist: redis>=2.10.6; extra == 'redis'
